sdecorator/__init__.py
sdecorator/api.py
sdecorator/pyarmor_runtime_000000/__init__.py
sdecorator/pyarmor_runtime_000000/pyarmor_runtime.pyd
sdecorator-0.1.1.dist-info/METADATA
sdecorator-0.1.1.dist-info/WHEEL
sdecorator-0.1.1.dist-info/RECORD
